odoo/addons/exportar_stock_editorial_xls/CHANGELOG.md
odoo/addons/exportar_stock_editorial_xls/README.md
odoo/addons/exportar_stock_editorial_xls/__init__.py
odoo/addons/exportar_stock_editorial_xls/__manifest__.py
odoo/addons/exportar_stock_editorial_xls/controllers/__init__.py
odoo/addons/exportar_stock_editorial_xls/controllers/export_stockinfo_xls.py
odoo/addons/exportar_stock_editorial_xls/doc/RELEASE_NOTES.md
odoo/addons/exportar_stock_editorial_xls/i18n_extra/es.po
odoo/addons/exportar_stock_editorial_xls/models/__init__.py
odoo/addons/exportar_stock_editorial_xls/models/product_category.py
odoo/addons/exportar_stock_editorial_xls/models/res_partner.py
odoo/addons/exportar_stock_editorial_xls/models/stock_warehouse.py
odoo/addons/exportar_stock_editorial_xls/security/ir.model.access.csv
odoo/addons/exportar_stock_editorial_xls/static/description/banner.png
odoo/addons/exportar_stock_editorial_xls/static/description/icon.png
odoo/addons/exportar_stock_editorial_xls/static/description/index.html
odoo/addons/exportar_stock_editorial_xls/static/description/images/advanced_stock.png
odoo/addons/exportar_stock_editorial_xls/static/description/images/banner.png
odoo/addons/exportar_stock_editorial_xls/static/description/images/barcode_scanning.jpeg
odoo/addons/exportar_stock_editorial_xls/static/description/images/checked.png
odoo/addons/exportar_stock_editorial_xls/static/description/images/cybrosys.png
odoo/addons/exportar_stock_editorial_xls/static/description/images/export.jpeg
odoo/addons/exportar_stock_editorial_xls/static/description/images/export.png
odoo/addons/exportar_stock_editorial_xls/static/description/images/export1.png
odoo/addons/exportar_stock_editorial_xls/static/description/images/export2.png
odoo/addons/exportar_stock_editorial_xls/static/description/images/export3.png
odoo/addons/exportar_stock_editorial_xls/static/description/images/inventory_valuation.png
odoo/addons/exportar_stock_editorial_xls/static/description/images/product_barcode.png
odoo_addon_exportar_stock_editorial_xls-17.0.1.1.1.2.dist-info/METADATA
odoo_addon_exportar_stock_editorial_xls-17.0.1.1.1.2.dist-info/WHEEL
odoo_addon_exportar_stock_editorial_xls-17.0.1.1.1.2.dist-info/top_level.txt
odoo_addon_exportar_stock_editorial_xls-17.0.1.1.1.2.dist-info/RECORD
