Metadata-Version: 2.1
Name: odoo-addon-exportar_stock_editorial_xls
Version: 17.0.1.1.1.2
Requires-Python: >=3.10
Requires-Dist: odoo-addon-gestion_editorial>=17.0dev,<17.1dev
Requires-Dist: odoo>=17.0a,<17.1dev
Summary: Muestra el stock actual de productos en la editorial.
Home-page: https://framagit.org/devcontrol
License: AGPL-3
Author: Colectivo DEVCONTROL
Classifier: Programming Language :: Python
Classifier: Framework :: Odoo
Classifier: Framework :: Odoo :: 17.0
Classifier: License :: OSI Approved :: GNU Affero General Public License v3
